procbridge/__init__.py
procbridge/const.py
procbridge/errors.py
procbridge/protocol.py
procbridge-1.2.2.dist-info/LICENSE
procbridge-1.2.2.dist-info/METADATA
procbridge-1.2.2.dist-info/WHEEL
procbridge-1.2.2.dist-info/top_level.txt
procbridge-1.2.2.dist-info/RECORD
