Metadata-Version: 2.1
Name: procbridge
Version: 1.2.2
Summary: A super-lightweight IPC (Inter-Process Communication) protocol over TCP socket.
Home-page: https://github.com/gongzhang/procbridge-python
Author: Gong Zhang
Author-email: gong@me.com
License: MIT License
Platform: any
Classifier: Programming Language :: Python :: 3
Classifier: License :: OSI Approved :: MIT License
Classifier: Operating System :: OS Independent
